<?xml version="1.0" encoding="utf-8"?>
<level width="804" height="480">
    <actor x="456" y="48" actor="1" type="walking" shoots="false" weapon="none" facing="right" life="3" explosion="1" animationSpeed="200" movementSpeed="1"/> <!-- ROW 4 COLUMN 38 -->
    <actor x="720" y="156" actor="7" type="walking" shoots="false" weapon="none" facing="right" life="3" explosion="1" animationSpeed="200" movementSpeed="1"/> <!-- ROW 13 COLUMN 60 -->
    <actor x="324" y="192" actor="7" type="walking" shoots="false" weapon="none" facing="left" life="3" explosion="1" animationSpeed="200" movementSpeed="1"/> <!-- ROW 16 COLUMN 27 -->
    <actor x="432" y="192" actor="15" type="standing" shoots="false" weapon="none" facing="right" life="3" explosion="1" animationSpeed="200" movementSpeed="0"/> <!-- ROW 18 COLUMN 37 -->
    <actor x="12" y="264" actor="7" type="walking" shoots="false" weapon="none" facing="left" life="3" explosion="1" animationSpeed="200" movementSpeed="1"/> <!-- ROW 22 COLUMN 1 -->
    <actor x="768" y="276" actor="15" type="standing" shoots="false" weapon="none" facing="right" life="3" explosion="1" animationSpeed="200" movementSpeed="0"/> <!-- ROW 24 COLUMN 64 -->
    <actor x="228" y="360" actor="7" type="walking" shoots="false" weapon="none" facing="left" life="3" explosion="1" animationSpeed="200" movementSpeed="1"/> <!-- ROW 30 COLUMN 19 -->
    <actor x="684" y="360" actor="1" type="walking" shoots="false" weapon="none" facing="right" life="3" explosion="1" animationSpeed="200" movementSpeed="1"/> <!-- ROW 30 COLUMN 57 -->
</level>